cdl_lsp/__init__.py
cdl_lsp/__main__.py
cdl_lsp/constants.py
cdl_lsp/py.typed
cdl_lsp/server.py
cdl_lsp/features/__init__.py
cdl_lsp/features/code_actions.py
cdl_lsp/features/completion.py
cdl_lsp/features/definition.py
cdl_lsp/features/diagnostics.py
cdl_lsp/features/document_symbols.py
cdl_lsp/features/explain.py
cdl_lsp/features/formatting.py
cdl_lsp/features/hover.py
cdl_lsp/features/preview.py
cdl_lsp/features/signature_help.py
cdl_lsp/features/snippets.py
gemmology_cdl_lsp-1.0.1.dist-info/licenses/LICENSE
gemmology_cdl_lsp-1.0.1.dist-info/METADATA
gemmology_cdl_lsp-1.0.1.dist-info/WHEEL
gemmology_cdl_lsp-1.0.1.dist-info/entry_points.txt
gemmology_cdl_lsp-1.0.1.dist-info/top_level.txt
gemmology_cdl_lsp-1.0.1.dist-info/RECORD
