Metadata-Version: 2.4
Name: gemmology-cdl-lsp
Version: 1.0.1
Summary: Language Server Protocol implementation for Crystal Description Language
Author-email: Fabian Schuh <fabian@gemmology.dev>
Maintainer-email: Fabian Schuh <fabian@gemmology.dev>
License: MIT
Project-URL: Homepage, https://cdl-lsp.gemmology.dev
Project-URL: Documentation, https://cdl-lsp.gemmology.dev/docs
Project-URL: Repository, https://github.com/gemmology-dev/cdl-lsp
Project-URL: Issues, https://github.com/gemmology-dev/cdl-lsp/issues
Project-URL: Changelog, https://github.com/gemmology-dev/cdl-lsp/blob/main/CHANGELOG.md
Keywords: crystallography,lsp,language-server,cdl,crystal,editor,vscode
Classifier: Development Status :: 5 - Production/Stable
Classifier: Intended Audience :: Developers
Classifier: Intended Audience :: Science/Research
Classifier: License :: OSI Approved :: MIT License
Classifier: Operating System :: OS Independent
Classifier: Programming Language :: Python :: 3
Classifier: Programming Language :: Python :: 3.10
Classifier: Programming Language :: Python :: 3.11
Classifier: Programming Language :: Python :: 3.12
Classifier: Programming Language :: Python :: 3.13
Classifier: Topic :: Scientific/Engineering
Classifier: Topic :: Text Editors :: Integrated Development Environments (IDE)
Classifier: Typing :: Typed
Requires-Python: >=3.10
License-File: LICENSE
Requires-Dist: gemmology-cdl-parser>=1.0.0
Requires-Dist: pygls>=1.0.0
Requires-Dist: lsprotocol>=2023.0.0
Provides-Extra: dev
Requires-Dist: pytest>=7.0; extra == "dev"
Requires-Dist: pytest-cov>=4.0; extra == "dev"
Requires-Dist: ruff>=0.1.0; extra == "dev"
Requires-Dist: mypy>=1.0; extra == "dev"
Provides-Extra: preview
Requires-Dist: gemmology-crystal-geometry>=1.0.0; extra == "preview"
Requires-Dist: gemmology-crystal-renderer>=1.0.0; extra == "preview"
Provides-Extra: all
Requires-Dist: gemmology-crystal-geometry>=1.0.0; extra == "all"
Requires-Dist: gemmology-crystal-renderer>=1.0.0; extra == "all"
Requires-Dist: gemmology-mineral-database>=1.0.0; extra == "all"
Provides-Extra: docs
Requires-Dist: mkdocs>=1.5; extra == "docs"
Requires-Dist: mkdocs-material>=9.0; extra == "docs"
Requires-Dist: mkdocstrings[python]>=0.24; extra == "docs"
Dynamic: license-file
